StormReactor/__init__.py
StormReactor/waterQuality.py
StormReactor-1.3.0.dist-info/LICENSE.txt
StormReactor-1.3.0.dist-info/METADATA
StormReactor-1.3.0.dist-info/WHEEL
StormReactor-1.3.0.dist-info/top_level.txt
StormReactor-1.3.0.dist-info/RECORD
