Metadata-Version: 2.1
Name: StormReactor
Version: 1.3.0
Summary: StormReactor: Python package for modelling any pollutant generation or treatment method in SWMM
Home-page: https://github.com/kLabUM/StormReactor
Author: Brooke Mason, Abhiram Mullapudi
Author-email: bemason@umich.edu, abhiramm@umich.edu
Keywords: swmm pyswmm pollutants modeling water-quality
Classifier: Programming Language :: Python :: 3
Classifier: License :: OSI Approved :: GNU Lesser General Public License v3 (LGPLv3)
Classifier: Operating System :: OS Independent
Requires-Python: >=3.6
License-File: LICENSE.txt
Requires-Dist: numpy (>=1.22)
Requires-Dist: pyswmm (>=1.2)
Requires-Dist: scipy (>=1.7)
